{
  "schema_version": "3.0",
  "feature_id": "fix-remove-phase-1-cluster-init",
  "events": [
    {
      "sid": "01-01",
      "p": "PREPARE",
      "s": "EXECUTED",
      "d": "PASS",
      "t": "2026-04-26T11:18:20Z"
    },
    {
      "sid": "01-01",
      "p": "RED_ACCEPTANCE",
      "s": "EXECUTED",
      "d": "PASS",
      "t": "2026-04-26T11:19:33Z"
    },
    {
      "sid": "01-01",
      "p": "RED_UNIT",
      "s": "SKIPPED",
      "d": "APPROVED_SKIP: regression test is a clap-parse assertion at the public surface; no unit decomposition required",
      "t": "2026-04-26T11:19:35Z"
    },
    {
      "sid": "01-01",
      "p": "GREEN",
      "s": "SKIPPED",
      "d": "APPROVED_SKIP: GREEN deferred to step 01-02 per bug-context.md single-commit constraint",
      "t": "2026-04-26T11:19:37Z"
    },
    {
      "sid": "01-01",
      "p": "COMMIT",
      "s": "SKIPPED",
      "d": "APPROVED_SKIP: deferred to step 01-02 per bug-context.md single-commit constraint",
      "t": "2026-04-26T11:19:38Z"
    },
    {
      "sid": "01-02",
      "p": "PREPARE",
      "s": "EXECUTED",
      "d": "PASS",
      "t": "2026-04-26T11:22:14Z"
    },
    {
      "sid": "01-02",
      "p": "RED_ACCEPTANCE",
      "s": "SKIPPED",
      "d": "APPROVED_SKIP: regression test landed in step 01-01; this step is GREEN-only",
      "t": "2026-04-26T11:22:16Z"
    },
    {
      "sid": "01-02",
      "p": "RED_UNIT",
      "s": "SKIPPED",
      "d": "APPROVED_SKIP: no unit decomposition needed for a deletion",
      "t": "2026-04-26T11:22:18Z"
    },
    {
      "sid": "01-02",
      "p": "GREEN",
      "s": "EXECUTED",
      "d": "PASS",
      "t": "2026-04-26T11:27:12Z"
    }
  ]
}